parameters_fooetall/__init__.py
parameters_fooetall/main.py
parameters_fooetall-0.1.dist-info/METADATA
parameters_fooetall-0.1.dist-info/WHEEL
parameters_fooetall-0.1.dist-info/top_level.txt
parameters_fooetall-0.1.dist-info/RECORD
